scripts/__init__.py
scripts/bundler.py
scripts/convert_to_jinja.py
scripts/create_agent.py
scripts/generate_configs.py
scripts/generate_goals.py
scripts/generate_reflection_delta.py
scripts/helpsteer3.py
scripts/migrate_scores.py
scripts/prune_scores.py
scripts/score_unscored_hypotheses.py
scripts/summarize_pattern_stats.py
scripts/txt_to_j2.py
scripts/update_run_configs.py
scripts/zip_project.py
stephanie/__init__.py
stephanie/cli.py
stephanie/constants.py
stephanie/main.py
stephanie/supervisor.py
stephanie/agents/__init__.py
stephanie/agents/auto_tuner.py
stephanie/agents/automind.py
stephanie/agents/base_agent.py
stephanie/agents/compiler_optimizer.py
stephanie/agents/cot_dspy_generator.py
stephanie/agents/cot_generator.py
stephanie/agents/debate.py
stephanie/agents/dots_planner.py
stephanie/agents/evolution.py
stephanie/agents/general_reasoner.py
stephanie/agents/generation.py
stephanie/agents/generic.py
stephanie/agents/idea_evaluator.py
stephanie/agents/idea_evolution.py
stephanie/agents/idea_innovation.py
stephanie/agents/idea_sharpening.py
stephanie/agents/judge.py
stephanie/agents/lats.py
stephanie/agents/lats_dspy.py
stephanie/agents/lats_original.py
stephanie/agents/lookahead.py
stephanie/agents/meta_review.py
stephanie/agents/method_planner.py
stephanie/agents/model_selector.py
stephanie/agents/mrq_scoring.py
stephanie/agents/mrq_strategy.py
stephanie/agents/pipeline.py
stephanie/agents/pipeline_comparison.py
stephanie/agents/pipeline_judge.py
stephanie/agents/pipeline_preference_trainer.py
stephanie/agents/planner.py
stephanie/agents/prompt_compiler.py
stephanie/agents/prompt_tuning.py
stephanie/agents/prompt_validation.py
stephanie/agents/proximity.py
stephanie/agents/ranking.py
stephanie/agents/recovery_parser.py
stephanie/agents/refiner.py
stephanie/agents/reflection.py
stephanie/agents/reflection_delta.py
stephanie/agents/review.py
stephanie/agents/rule_generator.py
stephanie/agents/rule_refiner.py
stephanie/agents/rule_tuner.py
stephanie-0.1.0.dist-info/licenses/LICENSE
stephanie-0.1.0.dist-info/METADATA
stephanie-0.1.0.dist-info/WHEEL
stephanie-0.1.0.dist-info/top_level.txt
stephanie-0.1.0.dist-info/RECORD
