Metadata-Version: 2.4
Name: stephanie
Version: 0.1.0
Summary: A modular DSPy-based pipeline for LLM-powered scientific hypothesis generation and ranking.
Author-email: Ernan Hughes <ernanhughes@gmail.com>
License: MIT License
Project-URL: Homepage, https://github.com/ernanhughes/co-ai
License-File: LICENSE
Dynamic: license-file
